Jam_Twitter_API/account_async.py
Jam_Twitter_API/account_sync.py
Jam_Twitter_API/constants.py
Jam_Twitter_API/errors.py
Jam_Twitter_API/util.py
Jam_Twitter_API-1.1.dist-info/LICENSE.txt
Jam_Twitter_API-1.1.dist-info/METADATA
Jam_Twitter_API-1.1.dist-info/WHEEL
Jam_Twitter_API-1.1.dist-info/top_level.txt
Jam_Twitter_API-1.1.dist-info/RECORD
