Metadata-Version: 2.1
Name: Jam_Twitter_API
Version: 1.1
Summary: Implementation of X/Twitter v1, v2, and GraphQL APIs
Author-email: Jaammerr <jaammer.dev@gmail.com>
Project-URL: Homepage, https://github.com/Jaammerr/Twitter-API
Project-URL: Issues, https://github.com/Jaammerr/Twitter-API/issues
Classifier: Programming Language :: Python :: 3
Classifier: License :: OSI Approved :: MIT License
Classifier: Operating System :: OS Independent
Requires-Python: >=3.10
License-File: LICENSE.txt
Requires-Dist: curl-cffi
Requires-Dist: pydantic
Requires-Dist: orjson
Requires-Dist: httpx
Requires-Dist: tqdm
